{"userid": 2826813753, "username": "悦悦是我啊Hey"}
{"userid": 6202660638, "username": "悦悦_祝杨蓉0603生日快乐"}
{"userid": 6202660638, "username": "悦悦_祝杨蓉0603生日快乐"}
{"userid": 6259905030, "username": "戚薇家小仙女"}
{"userid": 6206306155, "username": "用户6206306155"}
{"userid": 6305641253, "username": "丝缫细雨沾衣润"}
{"userid": 6466205390, "username": "我的条与块6466205390"}
{"userid": 1885350191, "username": "珠玉在前_Echo"}
{"userid": 3013437565, "username": "媛姐姐是个大吃货"}
{"userid": 5229297389, "username": "G-zhuliya"}
{"userid": 6474791597, "username": "溯雪沐笙"}
{"userid": 6466205390, "username": "我的条与块6466205390"}
{"userid": 3091599111, "username": "宣陈等等啊"}
{"userid": 6201416697, "username": "我觉得你们不行"}
{"userid": 5534014913, "username": "_江江酱"}
{"userid": 3163781454, "username": "xiaoruige352946131"}
{"userid": 2484938672, "username": "秋香满怀"}
{"userid": 5677545906, "username": "用户5677545906"}
{"userid": 6179541147, "username": "吉祥如意依依"}
{"userid": 6449017066, "username": "小毛驴Kathy"}
{"userid": 3987386613, "username": "田田up"}
{"userid": 5147270839, "username": "懒羊羊的春天66"}
{"userid": 1764763775, "username": "慧妹酱-"}
{"userid": 6138387325, "username": "00后原创歌手王源2yu5u"}
{"userid": 6138387325, "username": "00后原创歌手王源2yu5u"}
{"userid": 6138387325, "username": "00后原创歌手王源2yu5u"}
{"userid": 6138387325, "username": "00后原创歌手王源2yu5u"}
{"userid": 6457556237, "username": "宗耿禹_izqt"}
{"userid": 5088356534, "username": "卟璃---卟弃"}
{"userid": 5100451543, "username": "眼眸里映出的夏天"}
{"userid": 3974846249, "username": "汉水蝦VV"}
{"userid": 6360115488, "username": "1水冰依月"}
{"userid": 5039432298, "username": "用户7ltbrgi8p0"}
{"userid": 1629733005, "username": "晨钟慕顾VV"}
{"userid": 3281404165, "username": "半亩方田1130"}
{"userid": 3491946392, "username": "vv啊啊啊啊啊啊"}
{"userid": 2654573645, "username": "薰衣草的味道丶"}
{"userid": 2280164553, "username": "战豆小姐"}
{"userid": 2016621551, "username": "happy2828"}
{"userid": 5342828029, "username": "要不是字数限制我能取一个小说辣"}
{"userid": 2003624177, "username": "SSSSSSSSSShaw"}
{"userid": 1787989195, "username": "biubiubiupiubiubiu"}
{"userid": 5650184902, "username": "KiraYamato丶丶丶"}
{"userid": 2005424817, "username": "萌萌旳漂亮妈妈-"}
{"userid": 6409458593, "username": "w37200"}
{"userid": 1731132983, "username": "方嘉豪Fong-kaho"}
{"userid": 5235389532, "username": "俏妞家熊小晕"}
{"userid": 5481830843, "username": "历史-总是惊人的相似"}
{"userid": 2176987017, "username": "手机用户2176987017"}
{"userid": 6136186416, "username": "冷静的十七叔"}
{"userid": 6182600013, "username": "熊猫儿熊"}
{"userid": 5661789019, "username": "听故事基"}
{"userid": 1881236611, "username": "远离公知保智商"}
{"userid": 3317274447, "username": "阿掰猜呆额诶付该"}
{"userid": 5963533279, "username": "万阁飞雪"}
{"userid": 2454827064, "username": "张小杰的小火锅"}
{"userid": 3480090160, "username": "兜兜小星星"}
{"userid": 5812719396, "username": "aa认真不较真"}
{"userid": 6446026862, "username": "老卵的一塌糊涂"}
{"userid": 6349223827, "username": "静静静198610"}
{"userid": 6063025561, "username": "是的不是地"}
{"userid": 6006860905, "username": "粉丝小清流"}
{"userid": 3175677207, "username": "FY_Normcore"}
{"userid": 3980098195, "username": "后知后觉丶离歌轻叹"}
{"userid": 1853989423, "username": "盛夏小幸运"}
{"userid": 1960559287, "username": "北京YHANN"}
{"userid": 1883574447, "username": "硕三爷"}
{"userid": 2270324684, "username": "TTHAX"}
{"userid": 2896109167, "username": "翁大萌萌萌萌萌萌萌"}
{"userid": 1616265012, "username": "-Numero"}
{"userid": 3803457089, "username": "鹏鹏鹏爷丶"}
{"userid": 5904181657, "username": "杨修丶"}
{"userid": 5628920092, "username": "梦魇蚀骨S"}
{"userid": 5730330311, "username": "小猫的miimi"}
{"userid": 2643635940, "username": "Itswyh"}
{"userid": 2699504043, "username": "kyou大i在京都"}
{"userid": 3012868685, "username": "青瓦白房卖南纸"}
{"userid": 5506112801, "username": "许正瑞大魔王"}
{"userid": 2692628171, "username": "BornHater127"}
{"userid": 5976528044, "username": "安格子啊"}
{"userid": 3604463192, "username": "瑾瑾哟ovo"}
{"userid": 5308454051, "username": "黄瓜圆又圆5195131"}
{"userid": 3656183721, "username": "我看你宛若滞胀"}
{"userid": 3280503710, "username": "JL福乐"}
{"userid": 2454827064, "username": "张小杰的小火锅"}
{"userid": 6259905030, "username": "戚薇家小仙女"}
{"userid": 1005832007, "username": "叉烧_瓦特"}
{"userid": 5880930360, "username": "泡泡鱼的鱼丸子"}
{"userid": 6337713925, "username": "薄荷之夏y1128"}
{"userid": 1139851774, "username": "不是小乔的桥"}
{"userid": 6305641253, "username": "丝缫细雨沾衣润"}
{"userid": 5312548303, "username": "储形融丧町"}
{"userid": 5305094304, "username": "BBrSByfriB137841"}
{"userid": 5538653618, "username": "用户5538653618"}
{"userid": 3480090160, "username": "兜兜小星星"}
{"userid": 3951233163, "username": "张暮惜_"}
{"userid": 2547850963, "username": "SPRINGSSU"}
{"userid": 5846333566, "username": "是polaris"}
{"userid": 2454827064, "username": "张小杰的小火锅"}
{"userid": 1809658782, "username": "Carinoa_"}
{"userid": 6177423367, "username": "东北烤热面"}
{"userid": 5147270839, "username": "懒羊羊的春天66"}
{"userid": 6259905030, "username": "戚薇家小仙女"}
{"userid": 2158829084, "username": "张纪鹏丶"}
{"userid": 6202660638, "username": "悦悦_祝杨蓉0603生日快乐"}
{"userid": 5813914214, "username": "VV_黑龙江小波_1130"}
{"userid": 5744138883, "username": "阿拉灯的妈卖批"}
{"userid": 2632499413, "username": "_奕含"}
{"userid": 2564829960, "username": "-曾晓玲"}
{"userid": 1799472802, "username": "ME小涛"}
{"userid": 3480090160, "username": "兜兜小星星"}
{"userid": 5130809937, "username": "HLm_嘟啦喇"}
{"userid": 5883034434, "username": "包子22248"}
{"userid": 5796453782, "username": "你的陈昊天"}
{"userid": 5972889702, "username": "小秘密的想法"}
{"userid": 2383788632, "username": "阿三小木瓜"}
{"userid": 5647775618, "username": "谢飞蝶吖"}
{"userid": 6315103508, "username": "babysbreath薛"}
{"userid": 2826813753, "username": "悦悦是我啊Hey"}
{"userid": 6268102213, "username": "陈小函函函函函函函"}
{"userid": 5591047689, "username": "你瞅啥213"}
{"userid": 5758044722, "username": "-守护小奶烊"}
{"userid": 5905475696, "username": "她夏了夏天40350"}
{"userid": 5405838473, "username": "大鹏金翅工作室"}
{"userid": 5124359594, "username": "Xue鱼-"}
{"userid": 6135699347, "username": "滴哩呼噜"}
{"userid": 6237005438, "username": "榴莲牛奶牛角包2017"}
{"userid": 5251242353, "username": "用户5251242353"}
{"userid": 6456946645, "username": "撩人的球源"}
{"userid": 6055279184, "username": "八折猫"}
{"userid": 5606630844, "username": "郭妍MISS"}
{"userid": 6089703926, "username": "五玲脂"}
{"userid": 6035911181, "username": "太阳女神0728"}
{"userid": 2462441401, "username": "GX孤独泪"}
{"userid": 2948807120, "username": "南无邪的折纸扇"}
